DESCRIPTION.rst
LICENSE
MANIFEST.in
README.md
setup.py
pyaws/__init__.py
pyaws/_version.py
pyaws/colors.py
pyaws/environment.py
pyaws/helpers.py
pyaws/logd.py
pyaws/script_utils.py
pyaws/session.py
pyaws/statics.py
pyaws/awslambda/__init__.py
pyaws/awslambda/env.py
pyaws/awslambda/lambda_utils.py
pyaws/core/__init__.py
pyaws/core/create_client.py
pyaws/core/cross_account_utils.py
pyaws/core/loggers.py
pyaws/core/oscodes_unix.py
pyaws/core/oscodes_win.py
pyaws/dynamodb/__init__.py
pyaws/dynamodb/dynamodb.py
pyaws/dynamodb/table.py
pyaws/ec2/__init__.py
pyaws/ec2/ec2_utils.py
pyaws/ec2/snapshot_ops.py
pyaws/ec2/state.py
pyaws/s3/__init__.py
pyaws/s3/check_authenticated_s3.py
pyaws/s3/object_operations.py
pyaws/sts/__init__.py
pyaws/sts/cross_account_utils.py
pyaws/tags/__init__.py
pyaws/tags/bulk-modify-tags.py
pyaws/tags/copy-tags-all-instances.py
pyaws/tags/ec2-update-tags.py
pyaws/tags/tag_utils.py
pyaws/utils/__init__.py